pelican_bib/__init__.py
pelican_bib/bib.py
pelican_bib-0.2.7.dist-info/LICENSE
pelican_bib-0.2.7.dist-info/METADATA
pelican_bib-0.2.7.dist-info/WHEEL
pelican_bib-0.2.7.dist-info/top_level.txt
pelican_bib-0.2.7.dist-info/RECORD
