Metadata-Version: 2.1
Name: pelican-bib
Version: 0.2.7
Summary: Organize your scientific publications using Pelican and BibTeX
Home-page: https://github.com/scheunemann/pelican-bib
Author: Marcus M. Scheunemann
Author-email: find@mms.ai
License: UNKNOWN
Download-URL: https://github.com/scheunemann/pelican-bib/archive/0.2.7.zip
Platform: UNKNOWN
Classifier: Development Status :: 3 - Alpha
Classifier: Intended Audience :: Science/Research
Classifier: Intended Audience :: Developers
Classifier: License :: OSI Approved :: MIT License
Classifier: Programming Language :: Python
Classifier: Programming Language :: Python :: 3
Classifier: Topic :: Scientific/Engineering
Classifier: Operating System :: POSIX
Classifier: Operating System :: Unix
Classifier: Topic :: Software Development :: Libraries :: Python Modules
Classifier: Topic :: Text Processing
